ianthe/__init__.py
ianthe/__main__.py
ianthe/ianthe.py
ianthe/icon.ico
ianthe-2023.12.17.1.dist-info/LICENSE
ianthe-2023.12.17.1.dist-info/METADATA
ianthe-2023.12.17.1.dist-info/WHEEL
ianthe-2023.12.17.1.dist-info/top_level.txt
ianthe-2023.12.17.1.dist-info/RECORD
