Metadata-Version: 2.1
Name: ianthe
Version: 2023.12.17.1
Summary: A simple Python executables build tool
Project-URL: Homepage, https://github.com/thatsOven/ianthe
Classifier: Programming Language :: Python :: 3
Classifier: License :: OSI Approved :: MIT License
Classifier: Operating System :: OS Independent
Requires-Python: >=3.10
License-File: LICENSE
